{"OutputFileHashSum":"2AF81A64C3D3499CA46DBB91FBA7ED3A61899823364F0BB9B85CB4E961FF3C26","Converted":true,"OutputModifyDate":"2021-11-22T12:41:46.0047538Z","Metadatas":[],"MetadataTypes":[{"CategoryName":"VuGen.Replay","MetadataTypeName":"HP.LR.Vugen.NotifyTransaction","Id":1},{"CategoryName":"VuGen.Replay","MetadataTypeName":"HP.LR.Vugen.Iteration","Id":2},{"CategoryName":"VuGen.Replay","MetadataTypeName":"Utt.Debugger.Warning","Id":3},{"CategoryName":"VuGen.Replay","MetadataTypeName":"Utt.Debugger.Error","Id":4},{"CategoryName":"VuGen.Replay","MetadataTypeName":"HP.LR.Vugen.NotifySavingParameter","Id":5},{"CategoryName":"VuGen.Replay","MetadataTypeName":"HP.LR.Vugen.NotifyAny","Id":6}]}